pfsense_api/__init__.py
pfsense_api/parser.py
pfsense_api/supported_api.py
pfsense_api-0.1.1.dist-info/licenses/LICENSE
pfsense_api-0.1.1.dist-info/METADATA
pfsense_api-0.1.1.dist-info/WHEEL
pfsense_api-0.1.1.dist-info/top_level.txt
pfsense_api-0.1.1.dist-info/RECORD
