Metadata-Version: 2.4
Name: pfsense_api
Version: 0.1.1
Summary: Python API for monitoring PfSense firewalls.
Author-email: Thomas Dunteman <git@learningtopi.com>
License-Expression: MIT
Project-URL: bug tracker, https://github.com/LearningToPi/pfsense_api/issues
Project-URL: source code, https://github.com/LearningToPi/pfsense_api
Keywords: queue,thread,async
Classifier: Programming Language :: Python :: 3
Classifier: Topic :: Software Development :: Libraries :: Python Modules
Classifier: Topic :: System :: Networking :: Firewalls
Classifier: Topic :: System :: Networking :: Monitoring
Classifier: Topic :: System :: Monitoring
Requires-Python: >=3.10
License-File: LICENSE
Requires-Dist: certifi>=2023.11.17
Requires-Dist: charset-normalizer>=3.3.2
Requires-Dist: exceptiongroup>=1.2.0
Requires-Dist: idna>=3.6
Requires-Dist: iniconfig>=2.0.0
Requires-Dist: logging-handler>=1.0.7
Requires-Dist: lxml>=5.1.0
Requires-Dist: packaging>=23.2
Requires-Dist: pluggy>=1.3.0
Requires-Dist: pytest>=7.4.4
Requires-Dist: requests>=2.31.0
Requires-Dist: six>=1.16.0
Requires-Dist: tomli>=2.0.1
Requires-Dist: urllib3>=2.1.0
Requires-Dist: validators>=0.22.0
Dynamic: license-file
